nagini/__init__.py
nagini/app.py
naginirest-0.1.0.dist-info/LICENSE
naginirest-0.1.0.dist-info/METADATA
naginirest-0.1.0.dist-info/WHEEL
naginirest-0.1.0.dist-info/top_level.txt
naginirest-0.1.0.dist-info/RECORD
