Metadata-Version: 2.1
Name: naginirest
Version: 0.1.0
Summary: A Python RESTful Web Service Framework
Home-page: UNKNOWN
Author: ChenZhongrun
Author-email: UNKNOWN
License: UNKNOWN
Platform: UNKNOWN
